Workbook

Sheet README
A1: JSAN Pricing Templates – GIS, Telecom, PLA & LiDAR
A2: Formula-driven commercial models for internal costing, rate-card design and customer quotations.
A3: How to use this workbook
A4: Step | B4: Section | C4: Purpose
A5: 1 | B5: Start with Assumptions | C5: Set target gross margin, overhead, QA, rework, contingency, PM, complexity and volume discounts.
A6: 2 | B6: Update Role_Rates | C6: Replace illustrative monthly costs/productive hours with JSAN actual internal costs.
A7: 3 | B7: Choose a pricing model | C7: Use Hourly, FTE, Per Pole, PLA, Per Feature, Per km / sq km / tile, or Field Collection.
A8: 4 | B8: Review Scenario_Compare | C8: Compare hourly vs unit vs FTE economics before selecting the commercial model.
A9: 5 | B9: Build the quote | C9: Use Bid_Builder for line items, discounts, contingency and final gross margin.
A10: 6 | B10: Share Customer_RateCard | C10: Customer-facing view hides internal costs and exposes only units and sell rates.
A12: Color | B12: Meaning
A13: Yellow | B13: Editable input / assumption
A14: Light blue | B14: Formula / calculated output
A15: Green | B15: Summary / recommended price
A16: Red | B16: Warning / risk
A17: All rates | B17: Illustrative examples only – replace with actual JSAN costs and customer-specific assumptions
A18: Margin formula | B18: Sell Price = Total Cost ÷ (1 – Target Gross Margin). This is gross margin, not markup.

Sheet Assumptions
A1: Global Pricing Assumptions
A2: Edit yellow cells; all model sheets reference these assumptions.
A4: Parameter | B4: Value | D4: Complexity | E4: Multiplier | G4: Volume Threshold | H4: Discount %
A5: Base reporting currency | B5: USD | D5: Simple | E5: 0.85 | G5: 0 | H5: 0
A6: Target Gross Margin | B6: 0.35 | D6: Standard | E6: 1 | G6: 500 | H6: 0.03
A7: Corporate Overhead on Direct Labor | B7: 0.18 | D7: Medium | E7: 1.25 | G7: 2000 | H7: 0.05
A8: Default QA Effort % | B8: 0.15 | D8: Complex | E8: 1.6 | G8: 5000 | H8: 0.08
A9: Default Rework Buffer % | B9: 0.05 | G9: 10000 | H9: 0.1
A10: PM / Coordination % | B10: 0.08
A11: Contingency % | B11: 0.05
A12: Rush Premium % | B12: 0.2
A13: Annual Escalation % | B13: 0.05
A14: Minimum Project Fee | B14: 1500
A15: Standard Productive Hrs / Month | B15: 160
A16: Working Hrs / Day | B16: 8
A18: Volume discounts are commercial levers, not automatic recommendations. Validate against throughput, minimum commitment and customer risk.

Sheet Role_Rates
A1: Role Cost & Billing Rate Builder
A2: Illustrative starting point – replace monthly direct costs with current JSAN internal data.
A4: Role | B4: Delivery Location | C4: Monthly Direct Cost | D4: Productive Hrs/Mo | E4: Direct Cost/Hr | F4: Loaded Cost/Hr | G4: Suggested Sell/Hr | H4: Notes
A5: GIS Analyst | B5: India | C5: 900 | D5: 160 | E5: =C5/D5 -> 5.625 | F5: =E5*(1+Assumptions!$B$7) -> 6.6375 | G5: =F5/(1-Assumptions!$B$6) -> 10.211538 | H5: Digitization / data validation
A6: Senior GIS Analyst | B6: India | C6: 1300 | D6: 160 | E6: =C6/D6 -> 8.125 | F6: =E6*(1+Assumptions!$B$7) -> 9.5875 | G6: =F6/(1-Assumptions!$B$6) -> 14.75 | H6: Complex GIS / conflation
A7: QA Analyst | B7: India | C7: 1000 | D7: 160 | E7: =C7/D7 -> 6.25 | F7: =E7*(1+Assumptions!$B$7) -> 7.375 | G7: =F7/(1-Assumptions!$B$6) -> 11.346154 | H7: QC / audit
A8: LiDAR Analyst | B8: India | C8: 1200 | D8: 160 | E8: =C8/D8 -> 7.5 | F8: =E8*(1+Assumptions!$B$7) -> 8.85 | G8: =F8/(1-Assumptions!$B$6) -> 13.615385 | H8: Point cloud / viewer extraction
A9: Telecom Designer | B9: India | C9: 1500 | D9: 160 | E9: =C9/D9 -> 9.375 | F9: =E9*(1+Assumptions!$B$7) -> 11.0625 | G9: =F9/(1-Assumptions!$B$6) -> 17.019231 | H9: Pole / make-ready design
A10: PLA Engineer | B10: India | C10: 2200 | D10: 150 | E10: =C10/D10 -> 14.666667 | F10: =E10*(1+Assumptions!$B$7) -> 17.306667 | G10: =F10/(1-Assumptions!$B$6) -> 26.625641 | H10: Pole loading / engineering review
A11: Project Manager | B11: India | C11: 2500 | D11: 150 | E11: =C11/D11 -> 16.666667 | F11: =E11*(1+Assumptions!$B$7) -> 19.666667 | G11: =F11/(1-Assumptions!$B$6) -> 30.25641 | H11: Governance / customer management
A12: Data Operator | B12: India | C12: 750 | D12: 165 | E12: =C12/D12 -> 4.5454545 | F12: =E12*(1+Assumptions!$B$7) -> 5.3636364 | G12: =F12/(1-Assumptions!$B$6) -> 8.2517483 | H12: Desk operations
A13: Field Crew Lead | B13: Field | C13: 4200 | D13: 160 | E13: =C13/D13 -> 26.25 | F13: =E13*(1+Assumptions!$B$7) -> 30.975 | G13: =F13/(1-Assumptions!$B$6) -> 47.653846 | H13: Illustrative field cost
A14: Field Technician | B14: Field | C14: 2800 | D14: 160 | E14: =C14/D14 -> 17.5 | F14: =E14*(1+Assumptions!$B$7) -> 20.65 | G14: =F14/(1-Assumptions!$B$6) -> 31.769231 | H14: Illustrative field cost

Sheet DeskOps_Hourly
A1: Desk Operations – Hourly / T&M Pricing
A2: Use when scope is uncertain, exception-heavy, or customer wants transparent time-and-material billing.
A4: Activity | B4: Role | C4: Volume | D4: Minutes/Unit | E4: Manual Hrs | F4: Complexity | G4: Est. Hrs | H4: Cost/Hr | I4: Sell/Hr | J4: Internal Cost | K4: Base Revenue | L4: Contingency | M4: Rush? | N4: Quoted Revenue | O4: Gross Margin %
A5: Data ingestion / staging | B5: Data Operator | C5: 1000 | D5: 0.8 | E5: 0 | F5: Standard | G5: =IF(E5>0,E5,C5*D5/60)*VLOOKUP(F5,Assumptions!$D$5:$E$8,2,FALSE)*(1+Assumptions!$B$8+Assumptions!$B$9) -> 16 | H5: =IFERROR(VLOOKUP(B5,Role_Rates!$A$5:$G$14,6,FALSE),0) -> 5.3636364 | I5: =IFERROR(VLOOKUP(B5,Role_Rates!$A$5:$G$14,7,FALSE),0) -> 8.2517483 | J5: =G5*H5 -> 85.818182 | K5: =G5*I5 -> 132.02797 | L5: =K5*Assumptions!$B$11 -> 6.6013986 | M5: No | N5: =(K5+L5)*(1+IF(M5="Yes",Assumptions!$B$12,0)) -> 138.62937 | O5: =IF(N5=0,0,(N5-J5)/N5) -> 0.38095238
A6: Data validation / attribute review | B6: GIS Analyst | C6: 1000 | D6: 2.5 | E6: 0 | F6: Standard | G6: =IF(E6>0,E6,C6*D6/60)*VLOOKUP(F6,Assumptions!$D$5:$E$8,2,FALSE)*(1+Assumptions!$B$8+Assumptions!$B$9) -> 50 | H6: =IFERROR(VLOOKUP(B6,Role_Rates!$A$5:$G$14,6,FALSE),0) -> 6.6375 | I6: =IFERROR(VLOOKUP(B6,Role_Rates!$A$5:$G$14,7,FALSE),0) -> 10.211538 | J6: =G6*H6 -> 331.875 | K6: =G6*I6 -> 510.57692 | L6: =K6*Assumptions!$B$11 -> 25.528846 | M6: No | N6: =(K6+L6)*(1+IF(M6="Yes",Assumptions!$B$12,0)) -> 536.10577 | O6: =IF(N6=0,0,(N6-J6)/N6) -> 0.38095238
A7: GIS digitization / edit | B7: GIS Analyst | C7: 1000 | D7: 4 | E7: 0 | F7: Medium | G7: =IF(E7>0,E7,C7*D7/60)*VLOOKUP(F7,Assumptions!$D$5:$E$8,2,FALSE)*(1+Assumptions!$B$8+Assumptions!$B$9) -> 100 | H7: =IFERROR(VLOOKUP(B7,Role_Rates!$A$5:$G$14,6,FALSE),0) -> 6.6375 | I7: =IFERROR(VLOOKUP(B7,Role_Rates!$A$5:$G$14,7,FALSE),0) -> 10.211538 | J7: =G7*H7 -> 663.75 | K7: =G7*I7 -> 1021.1538 | L7: =K7*Assumptions!$B$11 -> 51.057692 | M7: No | N7: =(K7+L7)*(1+IF(M7="Yes",Assumptions!$B$12,0)) -> 1072.2115 | O7: =IF(N7=0,0,(N7-J7)/N7) -> 0.38095238
A8: Conflation / network correction | B8: Senior GIS Analyst | C8: 500 | D8: 6 | E8: 0 | F8: Complex | G8: =IF(E8>0,E8,C8*D8/60)*VLOOKUP(F8,Assumptions!$D$5:$E$8,2,FALSE)*(1+Assumptions!$B$8+Assumptions!$B$9) -> 96 | H8: =IFERROR(VLOOKUP(B8,Role_Rates!$A$5:$G$14,6,FALSE),0) -> 9.5875 | I8: =IFERROR(VLOOKUP(B8,Role_Rates!$A$5:$G$14,7,FALSE),0) -> 14.75 | J8: =G8*H8 -> 920.4 | K8: =G8*I8 -> 1416 | L8: =K8*Assumptions!$B$11 -> 70.8 | M8: No | N8: =(K8+L8)*(1+IF(M8="Yes",Assumptions!$B$12,0)) -> 1486.8 | O8: =IF(N8=0,0,(N8-J8)/N8) -> 0.38095238
A9: QA sampling / audit | B9: QA Analyst | C9: 1000 | D9: 1.2 | E9: 0 | F9: Standard | G9: =IF(E9>0,E9,C9*D9/60)*VLOOKUP(F9,Assumptions!$D$5:$E$8,2,FALSE)*(1+Assumptions!$B$8+Assumptions!$B$9) -> 24 | H9: =IFERROR(VLOOKUP(B9,Role_Rates!$A$5:$G$14,6,FALSE),0) -> 7.375 | I9: =IFERROR(VLOOKUP(B9,Role_Rates!$A$5:$G$14,7,FALSE),0) -> 11.346154 | J9: =G9*H9 -> 177 | K9: =G9*I9 -> 272.30769 | L9: =K9*Assumptions!$B$11 -> 13.615385 | M9: No | N9: =(K9+L9)*(1+IF(M9="Yes",Assumptions!$B$12,0)) -> 285.92308 | O9: =IF(N9=0,0,(N9-J9)/N9) -> 0.38095238
A10: Project coordination | B10: Project Manager | C10: 1 | D10: 0 | E10: 12 | F10: Standard | G10: =IF(E10>0,E10,C10*D10/60)*VLOOKUP(F10,Assumptions!$D$5:$E$8,2,FALSE)*(1+Assumptions!$B$8+Assumptions!$B$9) -> 14.4 | H10: =IFERROR(VLOOKUP(B10,Role_Rates!$A$5:$G$14,6,FALSE),0) -> 19.666667 | I10: =IFERROR(VLOOKUP(B10,Role_Rates!$A$5:$G$14,7,FALSE),0) -> 30.25641 | J10: =G10*H10 -> 283.2 | K10: =G10*I10 -> 435.69231 | L10: =K10*Assumptions!$B$11 -> 21.784615 | M10: No | N10: =(K10+L10)*(1+IF(M10="Yes",Assumptions!$B$12,0)) -> 457.47692 | O10: =IF(N10=0,0,(N10-J10)/N10) -> 0.38095238
A12: Model Summary | J12: Metric | K12: Value
J13: Total Hours | K13: =SUM(G5:G10) -> 300.4
J14: Total Internal Cost | K14: =SUM(J5:J10) -> 2462.0432
J15: Total Quoted Revenue | K15: =MAX(SUM(N5:N10),Assumptions!$B$14) -> 3977.1467

Sheet DeskOps_FTE
A1: Desk Operations – Dedicated FTE / Monthly Pricing
A2: Use for stable recurring work with predictable monthly demand and customer commitment.
A4: Role | B4: FTE Count | C4: Months | D4: Monthly Direct Cost/FTE | E4: Loaded Cost/FTE | F4: Sell Price/FTE/Month | G4: Total Cost | H4: Total Revenue | I4: Gross Margin % | J4: Comments
A5: Data Operator | B5: 3 | C5: 6 | D5: =IFERROR(VLOOKUP(A5,Role_Rates!$A$5:$C$14,3,FALSE),0) -> 750 | E5: =D5*(1+Assumptions!$B$7) -> 885 | F5: =E5/(1-Assumptions!$B$6) -> 1361.5385 | G5: =B5*C5*E5 -> 15930 | H5: =B5*C5*F5 -> 24507.692 | I5: =IF(H5=0,0,(H5-G5)/H5) -> 0.35 | J5: High-volume recurring desk ops
A6: GIS Analyst | B6: 4 | C6: 6 | D6: =IFERROR(VLOOKUP(A6,Role_Rates!$A$5:$C$14,3,FALSE),0) -> 900 | E6: =D6*(1+Assumptions!$B$7) -> 1062 | F6: =E6/(1-Assumptions!$B$6) -> 1633.8462 | G6: =B6*C6*E6 -> 25488 | H6: =B6*C6*F6 -> 39212.308 | I6: =IF(H6=0,0,(H6-G6)/H6) -> 0.35 | J6: Digitization / validation
A7: QA Analyst | B7: 1 | C7: 6 | D7: =IFERROR(VLOOKUP(A7,Role_Rates!$A$5:$C$14,3,FALSE),0) -> 1000 | E7: =D7*(1+Assumptions!$B$7) -> 1180 | F7: =E7/(1-Assumptions!$B$6) -> 1815.3846 | G7: =B7*C7*E7 -> 7080 | H7: =B7*C7*F7 -> 10892.308 | I7: =IF(H7=0,0,(H7-G7)/H7) -> 0.35 | J7: Quality gate
A8: Project Manager | B8: 0.5 | C8: 6 | D8: =IFERROR(VLOOKUP(A8,Role_Rates!$A$5:$C$14,3,FALSE),0) -> 2500 | E8: =D8*(1+Assumptions!$B$7) -> 2950 | F8: =E8/(1-Assumptions!$B$6) -> 4538.4615 | G8: =B8*C8*E8 -> 8850 | H8: =B8*C8*F8 -> 13615.385 | I8: =IF(H8=0,0,(H8-G8)/H8) -> 0.35 | J8: Governance
A10: FTE Summary | G10: Metric | H10: Value
G11: Total Cost | H11: =SUM(G5:G8) -> 57348
G12: Total Revenue | H12: =SUM(H5:H8) -> 88227.692

Sheet Telecom_Unit
A1: Telecom Operations – Unit Pricing
A2: Supports per pole, per application, per span and per inspection models.
A4: Activity | B4: Unit | C4: Volume | D4: Role | E4: Min/Unit | F4: Complexity | G4: Labor Cost/Unit | H4: Tool/Other/Unit | I4: QA % | J4: Cost/Unit | K4: Target Margin | L4: Volume Disc. | M4: Sell/Unit | N4: Total Cost | O4: Total Revenue | P4: Gross Margin % | Q4: Comments
A5: Application completeness review | B5: Application | C5: 25 | D5: Telecom Designer | E5: 45 | F5: Standard | G5: =(E5/60)*IFERROR(VLOOKUP(D5,Role_Rates!$A$5:$F$14,6,FALSE),0)*VLOOKUP(F5,Assumptions!$D$5:$E$8,2,FALSE) -> 8.296875 | H5: 0 | I5: 0.1 | J5: =(G5+H5)*(1+I5+Assumptions!$B$9+Assumptions!$B$11) -> 9.95625 | K5: =Assumptions!$B$6 -> 0.35 | L5: =VLOOKUP(C5,Assumptions!$G$5:$H$9,2,TRUE) -> 0 | M5: =(J5/(1-K5))*(1-L5) -> 15.317308 | N5: =J5*C5 -> 248.90625 | O5: =M5*C5 -> 382.93269 | P5: =IF(O5=0,0,(O5-N5)/O5) -> 0.35 | Q5: Permit intake / document review
A6: Desktop pole review | B6: Pole | C6: 2500 | D6: Telecom Designer | E6: 6 | F6: Standard | G6: =(E6/60)*IFERROR(VLOOKUP(D6,Role_Rates!$A$5:$F$14,6,FALSE),0)*VLOOKUP(F6,Assumptions!$D$5:$E$8,2,FALSE) -> 1.10625 | H6: 0.15 | I6: 0.15 | J6: =(G6+H6)*(1+I6+Assumptions!$B$9+Assumptions!$B$11) -> 1.5703125 | K6: =Assumptions!$B$6 -> 0.35 | L6: =VLOOKUP(C6,Assumptions!$G$5:$H$9,2,TRUE) -> 0.05 | M6: =(J6/(1-K6))*(1-L6) -> 2.2950721 | N6: =J6*C6 -> 3925.7812 | O6: =M6*C6 -> 5737.6803 | P6: =IF(O6=0,0,(O6-N6)/O6) -> 0.31578947 | Q6: Existing GIS/photos/data
A7: Attachment inventory / tracing | B7: Pole | C7: 2500 | D7: GIS Analyst | E7: 4 | F7: Medium | G7: =(E7/60)*IFERROR(VLOOKUP(D7,Role_Rates!$A$5:$F$14,6,FALSE),0)*VLOOKUP(F7,Assumptions!$D$5:$E$8,2,FALSE) -> 0.553125 | H7: 0.1 | I7: 0.15 | J7: =(G7+H7)*(1+I7+Assumptions!$B$9+Assumptions!$B$11) -> 0.81640625 | K7: =Assumptions!$B$6 -> 0.35 | L7: =VLOOKUP(C7,Assumptions!$G$5:$H$9,2,TRUE) -> 0.05 | M7: =(J7/(1-K7))*(1-L7) -> 1.1932091 | N7: =J7*C7 -> 2041.0156 | O7: =M7*C7 -> 2983.0228 | P7: =IF(O7=0,0,(O7-N7)/O7) -> 0.31578947 | Q7: Owner/attachment continuity
A8: Make-ready design review | B8: Pole | C8: 750 | D8: Telecom Designer | E8: 18 | F8: Complex | G8: =(E8/60)*IFERROR(VLOOKUP(D8,Role_Rates!$A$5:$F$14,6,FALSE),0)*VLOOKUP(F8,Assumptions!$D$5:$E$8,2,FALSE) -> 5.31 | H8: 0.5 | I8: 0.2 | J8: =(G8+H8)*(1+I8+Assumptions!$B$9+Assumptions!$B$11) -> 7.553 | K8: =Assumptions!$B$6 -> 0.35 | L8: =VLOOKUP(C8,Assumptions!$G$5:$H$9,2,TRUE) -> 0.03 | M8: =(J8/(1-K8))*(1-L8) -> 11.2714 | N8: =J8*C8 -> 5664.75 | O8: =M8*C8 -> 8453.55 | P8: =IF(O8=0,0,(O8-N8)/O8) -> 0.32989691 | Q8: Engineering/design check
A9: Post-construction inspection review | B9: Pole | C9: 1250 | D9: QA Analyst | E9: 5 | F9: Standard | G9: =(E9/60)*IFERROR(VLOOKUP(D9,Role_Rates!$A$5:$F$14,6,FALSE),0)*VLOOKUP(F9,Assumptions!$D$5:$E$8,2,FALSE) -> 0.61458333 | H9: 0.1 | I9: 0.15 | J9: =(G9+H9)*(1+I9+Assumptions!$B$9+Assumptions!$B$11) -> 0.89322917 | K9: =Assumptions!$B$6 -> 0.35 | L9: =VLOOKUP(C9,Assumptions!$G$5:$H$9,2,TRUE) -> 0.03 | M9: =(J9/(1-K9))*(1-L9) -> 1.3329728 | N9: =J9*C9 -> 1116.5365 | O9: =M9*C9 -> 1666.2159 | P9: =IF(O9=0,0,(O9-N9)/O9) -> 0.32989691 | Q9: As-built validation
A10: Closeout / GIS update | B10: Pole | C10: 2500 | D10: GIS Analyst | E10: 3 | F10: Standard | G10: =(E10/60)*IFERROR(VLOOKUP(D10,Role_Rates!$A$5:$F$14,6,FALSE),0)*VLOOKUP(F10,Assumptions!$D$5:$E$8,2,FALSE) -> 0.331875 | H10: 0.05 | I10: 0.1 | J10: =(G10+H10)*(1+I10+Assumptions!$B$9+Assumptions!$B$11) -> 0.45825 | K10: =Assumptions!$B$6 -> 0.35 | L10: =VLOOKUP(C10,Assumptions!$G$5:$H$9,2,TRUE) -> 0.05 | M10: =(J10/(1-K10))*(1-L10) -> 0.66975 | N10: =J10*C10 -> 1145.625 | O10: =M10*C10 -> 1674.375 | P10: =IF(O10=0,0,(O10-N10)/O10) -> 0.31578947 | Q10: System-of-record updates

Sheet PLA_PerPole
A1: Pole Loading Analysis (PLA) – Per Pole Pricing
A2: Builds cost per pole by engineering, GIS and QA effort; suitable for simple/standard/complex pole tiers.
A4: Pole Class | B4: Volume | C4: Engineer Min/Pole | D4: GIS Min/Pole | E4: QA Min/Pole | F4: Engineering Cost | G4: GIS Cost | H4: QA Cost | I4: Software/Tool Fee | J4: Contingency | K4: Total Cost/Pole | L4: Target Margin | M4: Volume Disc. | N4: Sell/Pole | O4: Total Revenue | P4: GM %
A5: Simple | B5: 500 | C5: 12 | D5: 4 | E5: 3 | F5: =(C5/60)*VLOOKUP("PLA Engineer",Role_Rates!$A$5:$F$14,6,FALSE) -> 3.4613333 | G5: =(D5/60)*VLOOKUP("GIS Analyst",Role_Rates!$A$5:$F$14,6,FALSE) -> 0.4425 | H5: =(E5/60)*VLOOKUP("QA Analyst",Role_Rates!$A$5:$F$14,6,FALSE) -> 0.36875 | I5: 0.5 | J5: =Assumptions!$B$11 -> 0.05 | K5: =(F5+G5+H5+I5)*(1+J5+Assumptions!$B$9) -> 5.2498417 | L5: =Assumptions!$B$6 -> 0.35 | M5: =VLOOKUP(B5,Assumptions!$G$5:$H$9,2,TRUE) -> 0.03 | N5: =(K5/(1-L5))*(1-M5) -> 7.8343791 | O5: =N5*B5 -> 3917.1896 | P5: =IF(O5=0,0,(O5-K5*B5)/O5) -> 0.32989691
A6: Standard | B6: 1500 | C6: 20 | D6: 5 | E6: 4 | F6: =(C6/60)*VLOOKUP("PLA Engineer",Role_Rates!$A$5:$F$14,6,FALSE) -> 5.7688889 | G6: =(D6/60)*VLOOKUP("GIS Analyst",Role_Rates!$A$5:$F$14,6,FALSE) -> 0.553125 | H6: =(E6/60)*VLOOKUP("QA Analyst",Role_Rates!$A$5:$F$14,6,FALSE) -> 0.49166667 | I6: 0.75 | J6: =Assumptions!$B$11 -> 0.05 | K6: =(F6+G6+H6+I6)*(1+J6+Assumptions!$B$9) -> 8.3200486 | L6: =Assumptions!$B$6 -> 0.35 | M6: =VLOOKUP(B6,Assumptions!$G$5:$H$9,2,TRUE) -> 0.03 | N6: =(K6/(1-L6))*(1-M6) -> 12.416073 | O6: =N6*B6 -> 18624.109 | P6: =IF(O6=0,0,(O6-K6*B6)/O6) -> 0.32989691
A7: Complex | B7: 600 | C7: 35 | D7: 8 | E7: 6 | F7: =(C7/60)*VLOOKUP("PLA Engineer",Role_Rates!$A$5:$F$14,6,FALSE) -> 10.095556 | G7: =(D7/60)*VLOOKUP("GIS Analyst",Role_Rates!$A$5:$F$14,6,FALSE) -> 0.885 | H7: =(E7/60)*VLOOKUP("QA Analyst",Role_Rates!$A$5:$F$14,6,FALSE) -> 0.7375 | I7: 1.25 | J7: =Assumptions!$B$11 -> 0.05 | K7: =(F7+G7+H7+I7)*(1+J7+Assumptions!$B$9) -> 14.264861 | L7: =Assumptions!$B$6 -> 0.35 | M7: =VLOOKUP(B7,Assumptions!$G$5:$H$9,2,TRUE) -> 0.03 | N7: =(K7/(1-L7))*(1-M7) -> 21.287562 | O7: =N7*B7 -> 12772.537 | P7: =IF(O7=0,0,(O7-K7*B7)/O7) -> 0.32989691
A8: Re-analysis / customer change | B8: 150 | C8: 18 | D8: 4 | E8: 4 | F8: =(C8/60)*VLOOKUP("PLA Engineer",Role_Rates!$A$5:$F$14,6,FALSE) -> 5.192 | G8: =(D8/60)*VLOOKUP("GIS Analyst",Role_Rates!$A$5:$F$14,6,FALSE) -> 0.4425 | H8: =(E8/60)*VLOOKUP("QA Analyst",Role_Rates!$A$5:$F$14,6,FALSE) -> 0.49166667 | I8: 0.5 | J8: =Assumptions!$B$11 -> 0.05 | K8: =(F8+G8+H8+I8)*(1+J8+Assumptions!$B$9) -> 7.2887833 | L8: =Assumptions!$B$6 -> 0.35 | M8: =VLOOKUP(B8,Assumptions!$G$5:$H$9,2,TRUE) -> 0 | N8: =(K8/(1-L8))*(1-M8) -> 11.213513 | O8: =N8*B8 -> 1682.0269 | P8: =IF(O8=0,0,(O8-K8*B8)/O8) -> 0.35

Sheet LiDAR_Feature
A1: LiDAR Viewer / Point Cloud Feature Extraction – Per Feature
A2: Use when deliverable is discrete asset or defect extraction from LiDAR, panoramas or point-cloud viewers.
A4: Feature Type | B4: Volume | C4: Analyst Min/Feature | D4: QA Min/Feature | E4: Complexity | F4: Analyst Cost | G4: QA Cost | H4: Viewer/Compute/Feature | I4: Rework % | J4: Cost/Feature | K4: Target Margin | L4: Volume Disc. | M4: Sell/Feature | N4: Total Cost | O4: Total Revenue | P4: GM % | Q4: Typical Output
A5: Pole / support structure | B5: 3000 | C5: 1.8 | D5: 0.5 | E5: Standard | F5: =(C5/60)*VLOOKUP("LiDAR Analyst",Role_Rates!$A$5:$F$14,6,FALSE)*VLOOKUP(E5,Assumptions!$D$5:$E$8,2,FALSE) -> 0.2655 | G5: =(D5/60)*VLOOKUP("QA Analyst",Role_Rates!$A$5:$F$14,6,FALSE) -> 0.061458333 | H5: 0.02 | I5: 0.04 | J5: =(F5+G5+H5)*(1+I5+Assumptions!$B$11) -> 0.37818458 | K5: =Assumptions!$B$6 -> 0.35 | L5: =VLOOKUP(B5,Assumptions!$G$5:$H$9,2,TRUE) -> 0.05 | M5: =(J5/(1-K5))*(1-L5) -> 0.55273131 | N5: =J5*B5 -> 1134.5538 | O5: =M5*B5 -> 1658.1939 | P5: =IF(O5=0,0,(O5-N5)/O5) -> 0.31578947 | Q5: Point + attributes
A6: Transformer / cabinet | B6: 800 | C6: 2.2 | D6: 0.6 | E6: Medium | F6: =(C6/60)*VLOOKUP("LiDAR Analyst",Role_Rates!$A$5:$F$14,6,FALSE)*VLOOKUP(E6,Assumptions!$D$5:$E$8,2,FALSE) -> 0.405625 | G6: =(D6/60)*VLOOKUP("QA Analyst",Role_Rates!$A$5:$F$14,6,FALSE) -> 0.07375 | H6: 0.03 | I6: 0.05 | J6: =(F6+G6+H6)*(1+I6+Assumptions!$B$11) -> 0.5603125 | K6: =Assumptions!$B$6 -> 0.35 | L6: =VLOOKUP(B6,Assumptions!$G$5:$H$9,2,TRUE) -> 0.03 | M6: =(J6/(1-K6))*(1-L6) -> 0.83615865 | N6: =J6*B6 -> 448.25 | O6: =M6*B6 -> 668.92692 | P6: =IF(O6=0,0,(O6-N6)/O6) -> 0.32989691 | Q6: Point + classification
A7: Crossarm / attachment | B7: 3500 | C7: 1.5 | D7: 0.5 | E7: Medium | F7: =(C7/60)*VLOOKUP("LiDAR Analyst",Role_Rates!$A$5:$F$14,6,FALSE)*VLOOKUP(E7,Assumptions!$D$5:$E$8,2,FALSE) -> 0.2765625 | G7: =(D7/60)*VLOOKUP("QA Analyst",Role_Rates!$A$5:$F$14,6,FALSE) -> 0.061458333 | H7: 0.02 | I7: 0.05 | J7: =(F7+G7+H7)*(1+I7+Assumptions!$B$11) -> 0.39382292 | K7: =Assumptions!$B$6 -> 0.35 | L7: =VLOOKUP(B7,Assumptions!$G$5:$H$9,2,TRUE) -> 0.05 | M7: =(J7/(1-K7))*(1-L7) -> 0.57558734 | N7: =J7*B7 -> 1378.3802 | O7: =M7*B7 -> 2014.5557 | P7: =IF(O7=0,0,(O7-N7)/O7) -> 0.31578947 | Q7: Asset + association
A8: Wire / conductor segment | B8: 5000 | C8: 1.2 | D8: 0.4 | E8: Complex | F8: =(C8/60)*VLOOKUP("LiDAR Analyst",Role_Rates!$A$5:$F$14,6,FALSE)*VLOOKUP(E8,Assumptions!$D$5:$E$8,2,FALSE) -> 0.2832 | G8: =(D8/60)*VLOOKUP("QA Analyst",Role_Rates!$A$5:$F$14,6,FALSE) -> 0.049166667 | H8: 0.02 | I8: 0.06 | J8: =(F8+G8+H8)*(1+I8+Assumptions!$B$11) -> 0.391127 | K8: =Assumptions!$B$6 -> 0.35 | L8: =VLOOKUP(B8,Assumptions!$G$5:$H$9,2,TRUE) -> 0.08 | M8: =(J8/(1-K8))*(1-L8) -> 0.55359514 | N8: =J8*B8 -> 1955.635 | O8: =M8*B8 -> 2767.9757 | P8: =IF(O8=0,0,(O8-N8)/O8) -> 0.29347826 | Q8: Line / connectivity
A9: Traffic sign / road asset | B9: 2500 | C9: 1 | D9: 0.3 | E9: Standard | F9: =(C9/60)*VLOOKUP("LiDAR Analyst",Role_Rates!$A$5:$F$14,6,FALSE)*VLOOKUP(E9,Assumptions!$D$5:$E$8,2,FALSE) -> 0.1475 | G9: =(D9/60)*VLOOKUP("QA Analyst",Role_Rates!$A$5:$F$14,6,FALSE) -> 0.036875 | H9: 0.01 | I9: 0.04 | J9: =(F9+G9+H9)*(1+I9+Assumptions!$B$11) -> 0.21186875 | K9: =Assumptions!$B$6 -> 0.35 | L9: =VLOOKUP(B9,Assumptions!$G$5:$H$9,2,TRUE) -> 0.05 | M9: =(J9/(1-K9))*(1-L9) -> 0.30965433 | N9: =J9*B9 -> 529.67188 | O9: =M9*B9 -> 774.13582 | P9: =IF(O9=0,0,(O9-N9)/O9) -> 0.31578947 | Q9: Point + attributes
A10: Guardrail / barrier | B10: 1200 | C10: 1.4 | D10: 0.4 | E10: Medium | F10: =(C10/60)*VLOOKUP("LiDAR Analyst",Role_Rates!$A$5:$F$14,6,FALSE)*VLOOKUP(E10,Assumptions!$D$5:$E$8,2,FALSE) -> 0.258125 | G10: =(D10/60)*VLOOKUP("QA Analyst",Role_Rates!$A$5:$F$14,6,FALSE) -> 0.049166667 | H10: 0.01 | I10: 0.04 | J10: =(F10+G10+H10)*(1+I10+Assumptions!$B$11) -> 0.34584792 | K10: =Assumptions!$B$6 -> 0.35 | L10: =VLOOKUP(B10,Assumptions!$G$5:$H$9,2,TRUE) -> 0.03 | M10: =(J10/(1-K10))*(1-L10) -> 0.51611151 | N10: =J10*B10 -> 415.0175 | O10: =M10*B10 -> 619.33381 | P10: =IF(O10=0,0,(O10-N10)/O10) -> 0.32989691 | Q10: Line
A11: Pavement defect / rut | B11: 700 | C11: 2.8 | D11: 0.8 | E11: Complex | F11: =(C11/60)*VLOOKUP("LiDAR Analyst",Role_Rates!$A$5:$F$14,6,FALSE)*VLOOKUP(E11,Assumptions!$D$5:$E$8,2,FALSE) -> 0.6608 | G11: =(D11/60)*VLOOKUP("QA Analyst",Role_Rates!$A$5:$F$14,6,FALSE) -> 0.098333333 | H11: 0.05 | I11: 0.08 | J11: =(F11+G11+H11)*(1+I11+Assumptions!$B$11) -> 0.91432067 | K11: =Assumptions!$B$6 -> 0.35 | L11: =VLOOKUP(B11,Assumptions!$G$5:$H$9,2,TRUE) -> 0.03 | M11: =(J11/(1-K11))*(1-L11) -> 1.3644478 | N11: =J11*B11 -> 640.02447 | O11: =M11*B11 -> 955.11343 | P11: =IF(O11=0,0,(O11-N11)/O11) -> 0.32989691 | Q11: Feature + measurement
A12: Building footprint / edge | B12: 900 | C12: 2.5 | D12: 0.7 | E12: Medium | F12: =(C12/60)*VLOOKUP("LiDAR Analyst",Role_Rates!$A$5:$F$14,6,FALSE)*VLOOKUP(E12,Assumptions!$D$5:$E$8,2,FALSE) -> 0.4609375 | G12: =(D12/60)*VLOOKUP("QA Analyst",Role_Rates!$A$5:$F$14,6,FALSE) -> 0.086041667 | H12: 0.04 | I12: 0.05 | J12: =(F12+G12+H12)*(1+I12+Assumptions!$B$11) -> 0.64567708 | K12: =Assumptions!$B$6 -> 0.35 | L12: =VLOOKUP(B12,Assumptions!$G$5:$H$9,2,TRUE) -> 0.03 | M12: =(J12/(1-K12))*(1-L12) -> 0.96354888 | N12: =J12*B12 -> 581.10938 | O12: =M12*B12 -> 867.19399 | P12: =IF(O12=0,0,(O12-N12)/O12) -> 0.32989691 | Q12: Polygon / line

Sheet GIS_Unit
A1: GIS / Mapping Unit Pricing – Per Feature, Record, km, sq km, Tile
A2: Supports planimetrics, geocoding, POI/address processing, linear mapping, imagery/LiDAR area work and map production.
A4: Service | B4: Unit | C4: Volume | D4: Role | E4: Productivity Units/Hr | F4: Complexity | G4: Labor Cost/Unit | H4: Data/Tool/Unit | I4: QA % | J4: Cost/Unit | K4: Target Margin | L4: Sell/Unit | M4: Total Cost | N4: Total Revenue | O4: GM %
A5: POI verification / enrichment | B5: POI | C5: 5000 | D5: GIS Analyst | E5: 18 | F5: Standard | G5: =(1/E5)*VLOOKUP(D5,Role_Rates!$A$5:$F$14,6,FALSE)*VLOOKUP(F5,Assumptions!$D$5:$E$8,2,FALSE) -> 0.36875 | H5: 0.02 | I5: 0.1 | J5: =(G5+H5)*(1+I5+Assumptions!$B$9+Assumptions!$B$11) -> 0.4665 | K5: =Assumptions!$B$6 -> 0.35 | L5: =J5/(1-K5) -> 0.71769231 | M5: =J5*C5 -> 2332.5 | N5: =L5*C5 -> 3588.4615 | O5: =IF(N5=0,0,(N5-M5)/N5) -> 0.35
A6: Point address verification | B6: Record | C6: 10000 | D6: GIS Analyst | E6: 24 | F6: Standard | G6: =(1/E6)*VLOOKUP(D6,Role_Rates!$A$5:$F$14,6,FALSE)*VLOOKUP(F6,Assumptions!$D$5:$E$8,2,FALSE) -> 0.2765625 | H6: 0.01 | I6: 0.1 | J6: =(G6+H6)*(1+I6+Assumptions!$B$9+Assumptions!$B$11) -> 0.343875 | K6: =Assumptions!$B$6 -> 0.35 | L6: =J6/(1-K6) -> 0.52903846 | M6: =J6*C6 -> 3438.75 | N6: =L6*C6 -> 5290.3846 | O6: =IF(N6=0,0,(N6-M6)/N6) -> 0.35
A7: Road / trail digitization | B7: km | C7: 1200 | D7: GIS Analyst | E7: 3.5 | F7: Medium | G7: =(1/E7)*VLOOKUP(D7,Role_Rates!$A$5:$F$14,6,FALSE)*VLOOKUP(F7,Assumptions!$D$5:$E$8,2,FALSE) -> 2.3705357 | H7: 0.1 | I7: 0.15 | J7: =(G7+H7)*(1+I7+Assumptions!$B$9+Assumptions!$B$11) -> 3.0881696 | K7: =Assumptions!$B$6 -> 0.35 | L7: =J7/(1-K7) -> 4.7510302 | M7: =J7*C7 -> 3705.8036 | N7: =L7*C7 -> 5701.2363 | O7: =IF(N7=0,0,(N7-M7)/N7) -> 0.35
A8: Building footprint extraction | B8: Feature | C8: 8000 | D8: GIS Analyst | E8: 10 | F8: Medium | G8: =(1/E8)*VLOOKUP(D8,Role_Rates!$A$5:$F$14,6,FALSE)*VLOOKUP(F8,Assumptions!$D$5:$E$8,2,FALSE) -> 0.8296875 | H8: 0.02 | I8: 0.15 | J8: =(G8+H8)*(1+I8+Assumptions!$B$9+Assumptions!$B$11) -> 1.0621094 | K8: =Assumptions!$B$6 -> 0.35 | L8: =J8/(1-K8) -> 1.6340144 | M8: =J8*C8 -> 8496.875 | N8: =L8*C8 -> 13072.115 | O8: =IF(N8=0,0,(N8-M8)/N8) -> 0.35
A9: Planimetric mapping | B9: sq km | C9: 120 | D9: Senior GIS Analyst | E9: 0.2 | F9: Complex | G9: =(1/E9)*VLOOKUP(D9,Role_Rates!$A$5:$F$14,6,FALSE)*VLOOKUP(F9,Assumptions!$D$5:$E$8,2,FALSE) -> 76.7 | H9: 4 | I9: 0.2 | J9: =(G9+H9)*(1+I9+Assumptions!$B$9+Assumptions!$B$11) -> 104.91 | K9: =Assumptions!$B$6 -> 0.35 | L9: =J9/(1-K9) -> 161.4 | M9: =J9*C9 -> 12589.2 | N9: =L9*C9 -> 19368 | O9: =IF(N9=0,0,(N9-M9)/N9) -> 0.35
A10: LiDAR classification / terrain QC | B10: sq km | C10: 250 | D10: LiDAR Analyst | E10: 0.45 | F10: Complex | G10: =(1/E10)*VLOOKUP(D10,Role_Rates!$A$5:$F$14,6,FALSE)*VLOOKUP(F10,Assumptions!$D$5:$E$8,2,FALSE) -> 31.466667 | H10: 1.5 | I10: 0.2 | J10: =(G10+H10)*(1+I10+Assumptions!$B$9+Assumptions!$B$11) -> 42.856667 | K10: =Assumptions!$B$6 -> 0.35 | L10: =J10/(1-K10) -> 65.933333 | M10: =J10*C10 -> 10714.167 | N10: =L10*C10 -> 16483.333 | O10: =IF(N10=0,0,(N10-M10)/N10) -> 0.35
A11: Orthomosaic / imagery QC | B11: sq km | C11: 180 | D11: QA Analyst | E11: 0.8 | F11: Medium | G11: =(1/E11)*VLOOKUP(D11,Role_Rates!$A$5:$F$14,6,FALSE)*VLOOKUP(F11,Assumptions!$D$5:$E$8,2,FALSE) -> 11.523438 | H11: 1 | I11: 0.15 | J11: =(G11+H11)*(1+I11+Assumptions!$B$9+Assumptions!$B$11) -> 15.654297 | K11: =Assumptions!$B$6 -> 0.35 | L11: =J11/(1-K11) -> 24.083534 | M11: =J11*C11 -> 2817.7734 | N11: =L11*C11 -> 4335.0361 | O11: =IF(N11=0,0,(N11-M11)/N11) -> 0.35
A12: Panorama metadata validation | B12: Panorama | C12: 15000 | D12: Data Operator | E12: 80 | F12: Standard | G12: =(1/E12)*VLOOKUP(D12,Role_Rates!$A$5:$F$14,6,FALSE)*VLOOKUP(F12,Assumptions!$D$5:$E$8,2,FALSE) -> 0.067045455 | H12: 0.005 | I12: 0.1 | J12: =(G12+H12)*(1+I12+Assumptions!$B$9+Assumptions!$B$11) -> 0.086454545 | K12: =Assumptions!$B$6 -> 0.35 | L12: =J12/(1-K12) -> 0.13300699 | M12: =J12*C12 -> 1296.8182 | N12: =L12*C12 -> 1995.1049 | O12: =IF(N12=0,0,(N12-M12)/N12) -> 0.35
A13: Map tile QA / release | B13: Tile | C13: 3000 | D13: QA Analyst | E13: 15 | F13: Standard | G13: =(1/E13)*VLOOKUP(D13,Role_Rates!$A$5:$F$14,6,FALSE)*VLOOKUP(F13,Assumptions!$D$5:$E$8,2,FALSE) -> 0.49166667 | H13: 0.01 | I13: 0.1 | J13: =(G13+H13)*(1+I13+Assumptions!$B$9+Assumptions!$B$11) -> 0.602 | K13: =Assumptions!$B$6 -> 0.35 | L13: =J13/(1-K13) -> 0.92615385 | M13: =J13*C13 -> 1806 | N13: =L13*C13 -> 2778.4615 | O13: =IF(N13=0,0,(N13-M13)/N13) -> 0.35

Sheet Field_Collection
A1: Field Collection Pricing – km / Mile / Pole / Site / Day
A2: Combines crew labor, vehicle/equipment, travel/per diem and back-office QA.
A4: Activity | B4: Unit | C4: Volume | D4: Crew Hrs/Unit | E4: Crew Cost/Hr | F4: Vehicle+Equip/Unit | G4: Travel+Per Diem/Unit | H4: Desk QA/Unit | I4: Contingency % | J4: Cost/Unit | K4: Target Margin | L4: Sell/Unit | M4: Total Cost | N4: Total Revenue | O4: GM % | P4: Notes
A5: Mobile mapping / street-view capture | B5: km | C5: 1200 | D5: 0.1 | E5: 55 | F5: 0.35 | G5: 0.1 | H5: 0.08 | I5: 0.05 | J5: =D5*E5+F5+G5+H5 -> 6.03 | K5: =Assumptions!$B$6 -> 0.35 | L5: =(J5*(1+I5))/(1-K5) -> 9.7407692 | M5: =J5*C5 -> 7236 | N5: =L5*C5 -> 11688.923 | O5: =IF(N5=0,0,(N5-M5)/N5) -> 0.38095238 | P5: Adjust speed/traffic/crew
A6: Pole field survey | B6: Pole | C6: 2500 | D6: 0.08 | E6: 55 | F6: 0.2 | G6: 0.05 | H6: 0.15 | I6: 0.05 | J6: =D6*E6+F6+G6+H6 -> 4.8 | K6: =Assumptions!$B$6 -> 0.35 | L6: =(J6*(1+I6))/(1-K6) -> 7.7538462 | M6: =J6*C6 -> 12000 | N6: =L6*C6 -> 19384.615 | O6: =IF(N6=0,0,(N6-M6)/N6) -> 0.38095238 | P6: Measurements/photos/GNSS
A7: Site verification | B7: Site | C7: 350 | D7: 0.6 | E7: 55 | F7: 3 | G7: 1 | H7: 1.5 | I7: 0.05 | J7: =D7*E7+F7+G7+H7 -> 38.5 | K7: =Assumptions!$B$6 -> 0.35 | L7: =(J7*(1+I7))/(1-K7) -> 62.192308 | M7: =J7*C7 -> 13475 | N7: =L7*C7 -> 21767.308 | O7: =IF(N7=0,0,(N7-M7)/N7) -> 0.38095238 | P7: POI / telecom / utility site
A8: Drone survey mobilization | B8: Day | C8: 12 | D8: 8 | E8: 90 | F8: 150 | G8: 50 | H8: 35 | I8: 0.08 | J8: =D8*E8+F8+G8+H8 -> 955 | K8: =Assumptions!$B$6 -> 0.35 | L8: =(J8*(1+I8))/(1-K8) -> 1586.7692 | M8: =J8*C8 -> 11460 | N8: =L8*C8 -> 19041.231 | O8: =IF(N8=0,0,(N8-M8)/N8) -> 0.39814815 | P8: Excludes aviation permits
A9: Trail / road evidence collection | B9: km | C9: 10000 | D9: 0.12 | E9: 55 | F9: 0.3 | G9: 0.1 | H9: 0.12 | I9: 0.05 | J9: =D9*E9+F9+G9+H9 -> 7.12 | K9: =Assumptions!$B$6 -> 0.35 | L9: =(J9*(1+I9))/(1-K9) -> 11.501538 | M9: =J9*C9 -> 71200 | N9: =L9*C9 -> 115015.38 | O9: =IF(N9=0,0,(N9-M9)/N9) -> 0.38095238 | P9: Geo-tagged photos/video

Sheet QA_QC
A1: QA / QC Pricing Template
A2: Standalone or bundled QA pricing by sampling rate, audit effort and rework validation.
A4: QA Activity | B4: Unit | C4: Production Volume | D4: Sample % | E4: Samples | F4: Min/Sample | G4: Role | H4: Cost/Hr | I4: Internal Cost | J4: Target Margin | K4: Sell Price | L4: Customer Unit Rate | M4: Total Revenue | N4: Notes
A5: Sampling QA | B5: Feature | C5: 10000 | D5: 0.1 | E5: =C5*D5 -> 1000 | F5: 1.2 | G5: QA Analyst | H5: =VLOOKUP(G5,Role_Rates!$A$5:$F$14,6,FALSE) -> 7.375 | I5: =E5*F5/60*H5 -> 147.5 | J5: =Assumptions!$B$6 -> 0.35 | K5: =I5/(1-J5) -> 226.92308 | L5: =IF(C5=0,0,K5/C5) -> 0.022692308 | M5: =K5 -> 226.92308 | N5: Routine statistical QA
A6: 100% release QC | B6: Pole | C6: 2500 | D6: 1 | E6: =C6*D6 -> 2500 | F6: 0.8 | G6: QA Analyst | H6: =VLOOKUP(G6,Role_Rates!$A$5:$F$14,6,FALSE) -> 7.375 | I6: =E6*F6/60*H6 -> 245.83333 | J6: =Assumptions!$B$6 -> 0.35 | K6: =I6/(1-J6) -> 378.20513 | L6: =IF(C6=0,0,K6/C6) -> 0.15128205 | M6: =K6 -> 378.20513 | N6: Critical telecom release
A7: Rework verification | B7: Finding | C7: 500 | D7: 1 | E7: =C7*D7 -> 500 | F7: 2 | G7: QA Analyst | H7: =VLOOKUP(G7,Role_Rates!$A$5:$F$14,6,FALSE) -> 7.375 | I7: =E7*F7/60*H7 -> 122.91667 | J7: =Assumptions!$B$6 -> 0.35 | K7: =I7/(1-J7) -> 189.10256 | L7: =IF(C7=0,0,K7/C7) -> 0.37820513 | M7: =K7 -> 189.10256 | N7: Customer/rework closure
A8: Engineering audit | B8: PLA Pole | C8: 600 | D8: 0.2 | E8: =C8*D8 -> 120 | F8: 6 | G8: PLA Engineer | H8: =VLOOKUP(G8,Role_Rates!$A$5:$F$14,6,FALSE) -> 17.306667 | I8: =E8*F8/60*H8 -> 207.68 | J8: =Assumptions!$B$6 -> 0.35 | K8: =I8/(1-J8) -> 319.50769 | L8: =IF(C8=0,0,K8/C8) -> 0.53251282 | M8: =K8 -> 319.50769 | N8: Complex pole sample

Sheet Scenario_Compare
A1: Commercial Model Scenario Comparator
A2: Compare Hourly/T&M, Per Unit and Dedicated FTE for the same scope.
A4: Input | B4: Value | D4: Model | E4: Internal Cost | F4: Customer Price | G4: Effective Unit Rate | H4: Comment
A5: Scope Volume | B5: 5000 | D5: Hourly / T&M | E5: =B5*B6/60*VLOOKUP(B7,Role_Rates!$A$5:$F$14,6,FALSE) -> 1659.375 | F5: =E5/(1-B10) -> 2552.8846 | G5: =F5/B5 -> 0.51057692 | H5: Best when scope/volume is uncertain
A6: Minutes per Unit | B6: 3 | D6: Per Unit | E6: =E5*(1+Assumptions!$B$8+Assumptions!$B$9+Assumptions!$B$11) -> 2074.2187 | F6: =E6/(1-B10) -> 3191.1058 | G6: =F6/B5 -> 0.63822115 | H6: Best when output definition and QA are stable
A7: Primary Role | B7: GIS Analyst | D7: Dedicated FTE | E7: =CEILING(B5*B6/60/(Assumptions!$B$15*B9),1)*B8*VLOOKUP(B7,Role_Rates!$A$5:$C$14,3,FALSE)*(1+Assumptions!$B$7) -> 6372 | F7: =E7/(1-B10) -> 9803.0769 | G7: =F7/B5 -> 1.9606154 | H7: Best for recurring committed volume
A8: Project Months | B8: 3
A9: FTE Utilization % | B9: 0.85
A10: Target Margin | B10: 0.35
A11: Minimum Monthly Volume Commitment | B11: 4000
A13: Decision guide: use unit pricing only when acceptance criteria are measurable and customer volume risk is understood. Use FTE when minimum monthly commitment protects utilization.

Sheet Bid_Builder
A1: Bid / Quote Builder
A2: Combine any workstream into one commercial quote. Yellow cells are customer/project inputs.
A3: Project / Customer | B3: Example Customer
A4: Currency | B4: USD
A5: Quote Validity (days) | B5: 30
A6: Commercial Discount % | B6: 0
A7: Project Contingency % | B7: 0.03
A8: Travel / One-time Cost | B8: 0
A9: Annual Escalation % | B9: 0.05
A10: Notes | B10: Replace sample line items with selected model outputs.
A13: Workstream | B13: Description | C13: Unit | D13: Qty | E13: Cost/Unit | F13: Sell/Unit | G13: Gross Cost | H13: Gross Revenue | I13: Line Discount % | J13: Net Revenue | K13: GM % | L13: Source Model
A14: Telecom | B14: Desktop pole review | C14: Pole | D14: 2500 | E14: =Telecom_Unit!J6 -> 1.5703125 | F14: =Telecom_Unit!M6 -> 2.2950721 | G14: =D14*E14 -> 3925.7812 | H14: =D14*F14 -> 5737.6803 | I14: 0 | J14: =H14*(1-I14) -> 5737.6803 | K14: =IF(J14=0,0,(J14-G14)/J14) -> 0.31578947 | L14: Telecom_Unit
A15: PLA | B15: Standard pole loading analysis | C15: Pole | D15: 1500 | E15: =PLA_PerPole!K6 -> 8.3200486 | F15: =PLA_PerPole!N6 -> 12.416073 | G15: =D15*E15 -> 12480.073 | H15: =D15*F15 -> 18624.109 | I15: 0 | J15: =H15*(1-I15) -> 18624.109 | K15: =IF(J15=0,0,(J15-G15)/J15) -> 0.32989691 | L15: PLA_PerPole
A16: LiDAR | B16: Pole extraction | C16: Feature | D16: 3000 | E16: =LiDAR_Feature!J5 -> 0.37818458 | F16: =LiDAR_Feature!M5 -> 0.55273131 | G16: =D16*E16 -> 1134.5538 | H16: =D16*F16 -> 1658.1939 | I16: 0 | J16: =H16*(1-I16) -> 1658.1939 | K16: =IF(J16=0,0,(J16-G16)/J16) -> 0.31578947 | L16: LiDAR_Feature
A17: GIS | B17: POI verification | C17: POI | D17: 5000 | E17: =GIS_Unit!J5 -> 0.4665 | F17: =GIS_Unit!L5 -> 0.71769231 | G17: =D17*E17 -> 2332.5 | H17: =D17*F17 -> 3588.4615 | I17: 0 | J17: =H17*(1-I17) -> 3588.4615 | K17: =IF(J17=0,0,(J17-G17)/J17) -> 0.35 | L17: GIS_Unit
A18: QA | B18: Sampling QA | C18: Feature | D18: 10000 | E18: =QA_QC!I5/QA_QC!C5 -> 0.01475 | F18: =QA_QC!L5 -> 0.022692308 | G18: =D18*E18 -> 147.5 | H18: =D18*F18 -> 226.92308 | I18: 0 | J18: =H18*(1-I18) -> 226.92308 | K18: =IF(J18=0,0,(J18-G18)/J18) -> 0.35 | L18: QA_QC
H21: Summary | I21: Value
H22: Total Cost | I22: =SUM(G14:G18)+B8 -> 20020.408
H23: Gross Revenue | I23: =SUM(J14:J18)*(1+B7) -> 30730.429
H24: Quote Discount | I24: =I23*B6 -> 0
H25: Final Quote | I25: =MAX(I23-I24,Assumptions!$B$14) -> 30730.429
H26: Overall Gross Margin | I26: =IF(I25=0,0,(I25-I22)/I25) -> 0.34851518

Sheet Customer_RateCard
A1: Customer-Facing Rate Card
A2: Use this sheet externally; internal cost columns are intentionally excluded.
A4: Service | B4: Unit | C4: Indicative Sell Rate | D4: Volume Basis | E4: Commercial Notes | F4: Internal Source
A5: GIS Analyst – T&M | B5: Hour | C5: =Role_Rates!G5 -> 10.211538 | D5: As requested | E5: Minimum 4-hour block | F5: Role_Rates
A6: Desktop Pole Review | B6: Pole | C6: =Telecom_Unit!M6 -> 2.2950721 | D6: 2500 poles | E6: Volume-tier pricing | F6: Telecom_Unit
A7: PLA – Standard Pole | B7: Pole | C7: =PLA_PerPole!N6 -> 12.416073 | D7: 1500 poles | E7: Complexity dependent | F7: PLA_PerPole
A8: LiDAR Pole Extraction | B8: Feature | C8: =LiDAR_Feature!M5 -> 0.55273131 | D8: 3000 features | E8: Feature definition required | F8: LiDAR_Feature
A9: POI Verification | B9: POI | C9: =GIS_Unit!L5 -> 0.71769231 | D9: 5000 POIs | E9: Evidence/source rules required | F9: GIS_Unit
A10: Road / Trail Digitization | B10: km | C10: =GIS_Unit!L7 -> 4.7510302 | D10: 1200 km | E10: Complexity/imagery dependent | F10: GIS_Unit
A11: Field Pole Survey | B11: Pole | C11: =Field_Collection!L6 -> 7.7538462 | D11: 2500 poles | E11: Travel/location excluded unless stated | F11: Field_Collection
A12: QA Sampling | B12: Production Unit | C12: =QA_QC!L5 -> 0.022692308 | D12: 10% sample | E12: Sampling plan to be agreed | F12: QA_QC

Sheet Dashboard
A1: Pricing Dashboard
A2: Portfolio-level view of example sell rates, total bid value and gross margin.
A3: KPI | B3: Value
A4: Target Gross Margin | B4: =Assumptions!B6 -> 0.35
A5: DeskOps Hourly Quote | B5: =DeskOps_Hourly!K15 -> 3977.1467
A6: Current Bid Builder Quote | B6: =Bid_Builder!I25 -> 30730.429
A7: Current Bid Builder GM | B7: =Bid_Builder!I26 -> 0.34851518
A10: Workstream | B10: Sell Rate | C10: Unit | D10: Example Volume | F10: Line Item | G10: Net Revenue | H10: GM %
A11: Telecom Desktop Pole | B11: =Telecom_Unit!M6 -> 2.2950721 | C11: Pole | D11: 2500 | F11: Telecom | G11: =Bid_Builder!J14 -> 5737.6803 | H11: =Bid_Builder!K14 -> 0.31578947
A12: PLA Standard | B12: =PLA_PerPole!N6 -> 12.416073 | C12: Pole | D12: 1500 | F12: PLA | G12: =Bid_Builder!J15 -> 18624.109 | H12: =Bid_Builder!K15 -> 0.32989691
A13: LiDAR Pole Feature | B13: =LiDAR_Feature!M5 -> 0.55273131 | C13: Feature | D13: 3000 | F13: LiDAR | G13: =Bid_Builder!J16 -> 1658.1939 | H13: =Bid_Builder!K16 -> 0.31578947
A14: GIS POI | B14: =GIS_Unit!L5 -> 0.71769231 | C14: POI | D14: 5000 | F14: GIS | G14: =Bid_Builder!J17 -> 3588.4615 | H14: =Bid_Builder!K17 -> 0.35
A15: Field Pole Survey | B15: =Field_Collection!L6 -> 7.7538462 | C15: Pole | D15: 2500 | F15: QA | G15: =Bid_Builder!J18 -> 226.92308 | H15: =Bid_Builder!K18 -> 0.35
A16: QA Sampling | B16: =QA_QC!L5 -> 0.022692308 | C16: Production Unit | D16: 10000

Sheet Sources
A1: Research Sources & Pricing-Structure References
A2: These sources support the use of hourly, per-pole, per-area and other unit-pricing structures. Public rates are examples only, not JSAN recommended prices.
A4: Source | B4: Pricing Structure Observed | C4: Why It Matters | D4: URL
A5: NYSEG / RG&E Make-Ready Engineering Unit Pricing | B5: Per pole | C5: Confirms per-pole application/engineering/inspection pricing is a common telecom utility commercial structure. | D5: https://www.rge.com/documents/40137/2123693/Pole%2BAttachment%2BPricing%2BForm%2BEff%2BFeb%2B2024_01.02.24.pdf/574fdc43-b082-d54b-2417-e834eb832538?t=1704400769485
A6: New York utility Make-Ready Unit Cost Schedule | B6: Per application and per pole, with volume tiers | C6: Shows tiered per-pole survey/inspection pricing and unit-cost schedules. | D6: https://documents.dps.ny.gov/public/Common/ViewDoc.aspx?DocRefId=%7B604B5697-0000-C76E-9317-F31B9A7A3895%7D&DocTitle=Pole+Attach+fees+and+charges
A7: CPS Energy Pole Attachment Unit Pricing | B7: Per pole + time & expense | C7: Shows PLA/application/design/inspection/closeout can be separately priced per pole. | D7: https://www.cpsenergy.com/content/dam/corporate/en/Documents/PoleAttachments/2017%20Pole%20Attachment%20Unit%20Pricing_effective%201Jan17.pdf
A8: USACE Mapping Manual | B8: Hourly/Daily and cost per unit area | C8: Supports hourly and area-based photogrammetry/mapping fee schedules. | D8: https://manualzz.com/doc/14104742/usace-mapping-manual
A9: Maricopa County Aerial Imagery Contract | B9: Per square mile | C9: Illustrates planimetrics, LiDAR, street-level imagery and QC priced per sq mile. | D9: https://poliscopic.com/documents/39618
A10: TCIL Tender – Survey & Data Processing | B10: Per sq km and lump sum | C10: Shows UAV LiDAR/optical survey charged per sq km and Web GIS implementation as lump sum. | D10: https://www.tcil.net.in/tender/pdf/corr_25f2577.pdf
